starstream/__init__.py
starstream/_base.py
starstream/_utils.py
starstream/_version.py
starstream/ace.py
starstream/downloader.py
starstream/dscovr.py
starstream/dst.py
starstream/goes.py
starstream/hinode.py
starstream/omni.py
starstream/proba_2.py
starstream/sdo.py
starstream/secchi.py
starstream/soho.py
starstream/swarm.py
starstream/typing.py
starstream/wind.py
starstream-1.1.3.dist-info/LICENSE
starstream-1.1.3.dist-info/METADATA
starstream-1.1.3.dist-info/WHEEL
starstream-1.1.3.dist-info/top_level.txt
starstream-1.1.3.dist-info/RECORD
