Metadata-Version: 2.1
Name: starstream
Version: 1.1.3
Summary: Asynchronous satellite data downloading for CDAWeb, JSOC, etc.
Home-page: https://github.com/Jorgedavyd/starstream
Author: Jorge David Enciso Martínez
Author-email: jorged.encyso@gmail.com
License: MIT
Project-URL: Bug Reports, https://github.com/Jorgedavyd/starstream/issues
Project-URL: Source, https://github.com/Jorgedavyd/starstream
Project-URL: Documentation, https://starstream.readthedocs.io/
Classifier: Development Status :: 5 - Production/Stable
Classifier: Intended Audience :: Science/Research
Classifier: Intended Audience :: Developers
Classifier: License :: OSI Approved :: MIT License
Classifier: Programming Language :: Python
Classifier: Programming Language :: Python :: 3
Classifier: Programming Language :: Python :: 3.9
Classifier: Programming Language :: Python :: 3.10
Classifier: Programming Language :: Python :: 3.11
Classifier: Programming Language :: Python :: 3.12
Classifier: Programming Language :: Python :: Implementation :: CPython
Classifier: Programming Language :: Python :: Implementation :: PyPy
Classifier: Operating System :: Microsoft :: Windows
Classifier: Operating System :: POSIX :: Linux
Classifier: Operating System :: MacOS :: MacOS X
Classifier: Topic :: Scientific/Engineering
Classifier: Topic :: Scientific/Engineering :: Astronomy
Classifier: Topic :: Scientific/Engineering :: Physics
Classifier: Topic :: Scientific/Engineering :: Mathematics
Classifier: Topic :: Scientific/Engineering :: Visualization
Classifier: Topic :: Scientific/Engineering :: Image Processing
Classifier: Topic :: Scientific/Engineering :: Information Analysis
Classifier: Topic :: Scientific/Engineering :: Artificial Intelligence
Classifier: Topic :: Software Development :: Libraries :: Python Modules
Classifier: Framework :: Matplotlib
Classifier: Framework :: Pytest
Classifier: Framework :: Sphinx
Classifier: Framework :: Jupyter
Classifier: Framework :: IPython
Classifier: Environment :: Console
Classifier: Environment :: Web Environment
Classifier: Natural Language :: English
Classifier: Typing :: Typed
Requires-Python: >=3.9
License-File: LICENSE
Requires-Dist: spacepy
Requires-Dist: astropy
Requires-Dist: xarray
Requires-Dist: tqdm
Requires-Dist: playwright
Requires-Dist: numpy
Requires-Dist: aiofiles
Requires-Dist: beautifulsoup4
Requires-Dist: pandas
Requires-Dist: polars
Requires-Dist: pillow
Requires-Dist: torch
Requires-Dist: joblib
Requires-Dist: aiohttp
Requires-Dist: viresclient
Provides-Extra: dev
Requires-Dist: pytest; extra == "dev"
Requires-Dist: black; extra == "dev"
Requires-Dist: isort; extra == "dev"
Requires-Dist: mypy; extra == "dev"
Requires-Dist: flake8; extra == "dev"
